Lab 09/FlipFlopD 1bit/FFD1B.v
//Diego A. Méndez
//Ejercicio 1

//FlipFlop de un bit
module ffD(input clk, reset, enable, input D, output reg Q);

    always @(posedge clk, posedge reset) begin
      //Hacemos que el reset haga Q = 0
      if (reset) begin
        Q <= 0;
        end
      //Hacemos que el Enable funcione
      else if (enable) begin
        Q <= D;
        end
    end //Always
endmodule

Lab 09/FlipFlopD 1bit/FFD1B_tb.v
module testbench();

  reg clk, reset;
  reg A, enable;
  wire Y;

//Iniciamos el clock
    always
      begin
      clk <= 0; reset<=0; #1 clk<=1; #1;

      end
//Llamamos al modelo FSM
      ffD U1(clk, reset, enable, A, Y);


      initial begin //iniciamos el display
            $display(" ");
            $display("  ");
            $display(" ");
            $display(" CLK | RST | EN | A | Y");
            $display("-------------------------");
            $monitor("  %b |  %b  |  %b  |  %b  | %b",clk ,reset, enable, A, Y);
               A=0; enable=1;
            #2 A=0; enable=1;
            #2 A=1; enable=1;
            #2 A=0; enable=1;
            #2 A=0; enable=1;
            #2 A=0; enable=1;
            #2 A=1; enable=1;
            #2 A=1; enable=1;
            #2 A=1; enable=1;
            //

            //  #2 reset=1;

          end

        initial
        #15 $finish;

        initial begin
          $dumpfile("FFD1B_tb.vcd");
          $dumpvars(0, testbench);
        end

      endmodule

Lab 09/FlipFlopD 1bit/FFD1B_tb.vcd
$date
	Sat Oct 31 10:37:34 2020
$end
$version
	Icarus Verilog
$end
$timescale
	1ps
$end
$scope module testbench $end
$var wire 1 ! Y $end
$var reg 1 " A $end
$var reg 1 # clk $end
$var reg 1 $ enable $end
$var reg 1 % reset $end
$scope module U1 $end
$var wire 1 " D $end
$var wire 1 # clk $end
$var wire 1 $ enable $end
$var wire 1 % reset $end
$var reg 1 ! Q $end
$upscope $end
$upscope $end
$enddefinitions $end
#0
$dumpvars
0%
1$
0#
0"
x!
$end
#1
0!
1#
#2
0#
#3
1#
#4
0#
1"
#5
1!
1#
#6
0#
0"
#7
0!
1#
#8
0#
#9
1#
#10
0#
#11
1#
#12
0#
1"
#13
1!
1#
