Lab 03/Tabla01_SOP/tabla01POS.v
module tabla01POS();

//POS tabla01

  wire outAN,outBN,outCN,out01,out02,out03,outres;

  reg inA,inB,inC;

  not U1 (outAN, inA);
  not U2 (outBN, inB);
  not U3 (outCN, inC);

  or U4 (out01,inA,inB,outCN);
  or U5 (out02,inA,outBN,outCN);
  or U6 (out03,outAN,outBN,inC);
  and U4(outres,out01,out02,out03);

  initial begin

    $display("A B C | Y");
    $display("---------");
    $monitor("%b %b %b %b", inA, inB, inC, outres);
    #1 inA=0; inB=0; inC=0;
    #1 inA=0; inB=0; inC=1;
    #1 inA=0; inB=1; inC=0;
    #1 inA=0; inB=1; inC=1;
    #1 inA=1; inB=0; inC=0;
    #1 inA=1; inB=0; inC=1;
    #1 inA=1; inB=1; inC=0;
    #1 inA=1; inB=1; inC=1;
    #1 $finish;
  end

  initial
    begin
      $dumpfile("tabla01POS_tb.vcd");
      $dumpvars(0,tabla01POS);
    end

endmodule

Lab 03/Tabla01_SOP/tabla01POS_tb.vcd
$date
	Fri Jul 31 22:53:44 2020
$end
$version
	Icarus Verilog
$end
$timescale
	1ps
$end
$scope module tabla01POS $end
$var wire 1 ! out01 $end
$var wire 1 " out02 $end
$var wire 1 # out03 $end
$var wire 1 $ outAN $end
$var wire 1 % outBN $end
$var wire 1 & outCN $end
$var wire 1 ' outres $end
$var reg 1 ( inA $end
$var reg 1 ) inB $end
$var reg 1 * inC $end
$upscope $end
$enddefinitions $end
#0
$dumpvars
x*
x)
x(
x'
x&
x%
x$
x#
x"
x!
$end
#1
1'
1!
1"
1#
1&
1%
1$
0*
0)
0(
#2
0'
0!
0&
1*
#3
1'
1&
1!
0%
0*
1)
#4
0'
0"
0&
1*
#5
1'
1&
1%
1"
0$
0*
0)
1(
#6
0&
1*
#7
0'
0#
1&
0%
0*
1)
#8
1'
1#
0&
1*
