Lab 06/Ejercicio 1/FSM.v
//Diego A. Méndez
//Ejercicio 1

//FlipFlop del ejercicio 5
module ffD(input clk, reset, input D, output reg Q);

    always @(posedge clk, posedge reset) begin
      //Hacemos que el reset haga Q = 0
      if (reset) begin
        Q <= 0;
        end
      //Hacemos que Q se vuelva D
      else
        Q <= D;
      end
endmodule
//Modulo para FSM
module FSM(input wire A, B, clk, reset, output Y );
  wire Sf1, Sf0;
  wire S1, S0;
//negamos los cables de estado
  not(nS1, S1);
  not(nS0, S0);

//colocamos las ecuaciones del estado futuro

  assign Sf1= S0 & B + S1 & A & B;
  assign Sf0= nS1 & nS0 & A;
  assign Y= S1 & A & B;
// conectamos los flip flops
  ffD U1(clk, reset, Sf1, S1);
  ffD U2(clk, reset, Sf0, S0);




endmodule

Lab 06/Ejercicio 1/FSM_tb.v
//Diego A. Méndez
//TestBench Ejercicio5

module testbench();

  reg clk, reset;
  reg A, B;
  wire Y;

//Iniciamos el clock
    always
      begin
      clk <= 0; reset<=0; #1 clk<=1; #1;

      end
//Llamamos al modelo FSM
      FSM U1(A, B, clk, reset, Y);


      initial begin //iniciamos el display
            $display(" ");
            $display("  ");
            $display(" ");
            $display("CLK | RST | A | B | Y");
            $display("----------");
            $monitor("%b | %b | %b | %b | %b",clk ,reset, A, B, Y);
             A=0; B=0;
            #2 A=0; B=1;
            #2 A=1; B=0;
            #2 A=1; B=1;
            #2 A=0; B=0;
            #2 A=0; B=1;
            #2 A=1; B=0;
            #2 A=1; B=1;
            #2 A=1; B=1;
            //

            //  #2 reset=1;

          end

        initial
        #15 $finish;

        initial begin
          $dumpfile("FSM_tb.vcd");
          $dumpvars(0, testbench);
        end

      endmodule

Lab 06/Ejercicio 1/FSM_tb.vcd
$date
	Sat Oct 10 17:02:09 2020
$end
$version
	Icarus Verilog
$end
$timescale
	1ps
$end
$scope module testbench $end
$var wire 1 ! Y $end
$var reg 1 " A $end
$var reg 1 # B $end
$var reg 1 $ clk $end
$var reg 1 % reset $end
$scope module U1 $end
$var wire 1 " A $end
$var wire 1 # B $end
$var wire 1 & Sf0 $end
$var wire 1 ' Sf1 $end
$var wire 1 ! Y $end
$var wire 1 $ clk $end
$var wire 1 ( nS0 $end
$var wire 1 ) nS1 $end
$var wire 1 % reset $end
$var wire 1 * S1 $end
$var wire 1 + S0 $end
$scope module U1 $end
$var wire 1 ' D $end
$var wire 1 $ clk $end
$var wire 1 % reset $end
$var reg 1 * Q $end
$upscope $end
$scope module U2 $end
$var wire 1 & D $end
$var wire 1 $ clk $end
$var wire 1 % reset $end
$var reg 1 + Q $end
$upscope $end
$upscope $end
$upscope $end
$enddefinitions $end
#0
$dumpvars
x+
x*
x)
x(
0'
0&
0%
0$
0#
0"
0!
$end
#1
1)
1(
0*
0+
1$
#2
0$
1#
#3
1$
#4
0$
1&
0#
1"
#5
0&
0(
1+
1$
#6
0$
1'
1#
#7
0'
1!
1(
0)
0+
1*
1$
#8
0$
0!
0#
0"
#9
1)
0*
1$
#10
0$
1#
#11
1$
#12
0$
1&
0#
1"
#13
0&
0(
1+
1$
#14
0$
1'
1#
#15
0'
1!
1(
0)
0+
1*
1$
