Lab 03/Tabla02_SOP/tabla02SOP.v
module tabla02SOP();

//SOP tabla02

  wire outAN,outBN,outCN,out01,out02,out03,out04,outres;

  reg inA,inB,inC;

  not U1 (outAN, inA);
  not U2 (outBN, inB);
  not U3 (outCN, inC);

  and U4 (out01,outAN,outBN,inC);
  and U5 (out02,inA,inB,outCN);
  and U6 (out03,inA,inB,inC);
  or U4(outres,out01,out02,out03);

  initial begin

    $display("A B C | Y");
    $display("---------");
    $monitor("%b %b %b %b",inA,inB,inC,outres);
       inA=0; inB=0; inC=0;
    #1 inA=0; inB=0; inC=1;
    #1 inA=0; inB=1; inC=0;
    #1 inA=0; inB=1; inC=1;
    #1 inA=1; inB=0; inC=0;
    #1 inA=1; inB=0; inC=1;
    #1 inA=1; inB=1; inC=0;
    #1 inA=1; inB=1; inC=1;
    $finish;
  end

// no olvidar cambiar el dump
  initial
    begin
      $dumpfile("tabla02SOP_tb.vcd");
      $dumpvars(0,tabla02SOP);
  end

endmodule

Lab 03/Tabla02_SOP/tabla02SOP_tb.vcd
$date
	Fri Jul 31 23:40:22 2020
$end
$version
	Icarus Verilog
$end
$timescale
	1ps
$end
$scope module tabla02SOP $end
$var wire 1 ! out01 $end
$var wire 1 " out02 $end
$var wire 1 # out03 $end
$var wire 1 $ outAN $end
$var wire 1 % outBN $end
$var wire 1 & outCN $end
$var wire 1 ' outres $end
$var reg 1 ( inA $end
$var reg 1 ) inB $end
$var reg 1 * inC $end
$upscope $end
$enddefinitions $end
#0
$dumpvars
0*
0)
0(
0'
1&
1%
1$
0#
0"
0!
$end
#1
1'
1!
0&
1*
#2
0'
0!
1&
0%
0*
1)
#3
0&
1*
#4
1&
1%
0$
0*
0)
1(
#5
0&
1*
#6
1'
1"
1&
0%
0*
1)
#7
0"
1#
0&
1*
