Lab 08/Ejercicio 1 Contador/Contador.v
//Diego A. Méndez
//Ejercicio 1
//Contador de 12bits


module contador(input wire clk, reset, EN, load, input wire[11:0] inpload, output reg[11:0] Q);

    wire D[11:0];

      always @(posedge clk, posedge reset, load) begin
        //Hacemos que el reset haga Q = 0
        if (reset) begin
          Q <= 12'b0;
        end

        //Hacemos que Q se 10 cuando sea load
        else if (load) begin
            Q <= inpload;
        end

        //Hacemos que Q sea D
        else if (EN) begin
            Q <= Q +1;
        end
      end

endmodule

Lab 08/Ejercicio 1 Contador/Contador_tb.v
//Diego A. Méndez
//Contador TestBench
module testbench();

  reg clk, reset, EN, Load;
  reg[11:0] InputLoad;
  wire[11:0] Y;

//Iniciamos el clock
    always
      begin
      clk <= 0; #1 clk<=1; #1;
      end
//Llamamos al modulo de contador
      contador U1(clk, reset, EN, Load, InputLoad, Y);


      initial begin //iniciamos el display
            reset=1; Load=0;
            #1
            $display(" ");
            $display("  ");
            $display(" ");
            $display("CLK| RST | Enable | Load |    InputLoad    |      Y");
            $display("---------------------------------------------------");
            $monitor("| %b |  %b |   %b   |   %b   |   %b  |  %b ",clk ,reset, EN, Load, InputLoad, Y);
             reset=0; EN=1; Load=0; InputLoad=001001001001;
            #1 reset=0; EN=0; Load=0;
            #1 reset=0; EN=0; Load=0;
            #1 reset=0; EN=1; Load=0;
            #1 reset=0; EN=1; Load=0;
            #1 reset=0; EN=1; Load=0;
            #1 reset=0; EN=1; Load=0;
            #1 reset=0; EN=1; Load=0;
            #1 reset=0; EN=1; Load=0;
            #1 reset=0; EN=1; Load=0;
            #1 reset=0; EN=1; Load=1;
            #1 reset=0; EN=1; Load=0;
            #1 reset=0; EN=1; Load=0;
            #1 reset=0; EN=1; Load=0;
            #1 reset=0; EN=1; Load=0;
            #1 reset=0; EN=0; Load=0;
            #1 reset=0; EN=0; Load=0;


          end

        initial
        #30 $finish;

        initial begin
          $dumpfile("Contador_tb.vcd");
          $dumpvars(0, testbench);
        end

      endmodule

Lab 08/Ejercicio 1 Contador/Contador_tb.vcd
$date
	Sat Oct 24 13:26:21 2020
$end
$version
	Icarus Verilog
$end
$timescale
	1ps
$end
$scope module testbench $end
$var wire 12 ! Y [11:0] $end
$var reg 1 " EN $end
$var reg 12 # InputLoad [11:0] $end
$var reg 1 $ Load $end
$var reg 1 % clk $end
$var reg 1 & reset $end
$scope module U1 $end
$var wire 1 " EN $end
$var wire 1 % clk $end
$var wire 12 ' inpload [11:0] $end
$var wire 1 $ load $end
$var wire 1 & reset $end
$var reg 12 ( Q [11:0] $end
$upscope $end
$upscope $end
$enddefinitions $end
#0
$dumpvars
b0 (
bx '
1&
0%
0$
bx #
x"
b0 !
$end
#1
b1 !
b1 (
1%
b101001 #
b101001 '
1"
0&
#2
0%
0"
#3
1%
#4
0%
1"
#5
b10 !
b10 (
1%
#6
0%
#7
b11 !
b11 (
1%
#8
0%
#9
b100 !
b100 (
1%
#10
0%
#11
b101001 !
b101001 (
1%
1$
#12
b101010 !
b101010 (
0%
0$
#13
b101011 !
b101011 (
1%
#14
0%
#15
b101100 !
b101100 (
1%
#16
0%
0"
