Lab 09/FlipFlop T/FFT.v
//Diego A. Méndez
//Ejercicio2

module ffD(input clk, reset, enable, input D, output reg Q);

    always @(posedge clk, posedge reset) begin
      //Hacemos que el reset haga Q = 0
      if (reset) begin
        Q <= 0;
        end
      //Hacemos que el Enable funcione
      else if (enable) begin
        Q <= D;
        end
    end //Always
endmodule

module ffT (input clk, reset, enable, output wire Q);

  wire jumper;
  not(jumper, Q);

  ffD U1(clk, reset, enable, jumper, Q);



endmodule // ffT

Lab 09/FlipFlop T/FFT_tb.v
//Diego A. Méndez
//Ejercicio2
//TestBench
module testbench();

  reg clk, reset, enable;
  wire Y;

//Iniciamos el clock
    always
      begin
      clk <= 0; reset<=0; #1 clk<=1; #1;

      end
//Llamamos al modelo FSM
      ffT U1(clk, reset, enable, Y);


      initial begin //iniciamos el display
      reset=1; #1 reset=0;
            $display(" ");
            $display("  ");
            $display(" ");
            $display(" CLK | RST | EN | Y");
            $display("-------------------------");
            $monitor("  %b |  %b  |  %b  | %b",clk ,reset, enable, Y);
                enable=1;
            #2  enable=1;
            #2  enable=1;
            #2  enable=1;
            #2  enable=0;
            #2  enable=0;
            #2  enable=1;
            #2  enable=1;
            #2  enable=1;
            //

            //  #2 reset=1;

          end

        initial
        #15 $finish;

        initial begin
          $dumpfile("FFT_tb.vcd");
          $dumpvars(0, testbench);
        end

      endmodule

Lab 09/FlipFlop T/FFT_tb.vcd
$date
	Fri Oct 30 18:19:37 2020
$end
$version
	Icarus Verilog
$end
$timescale
	1ps
$end
$scope module testbench $end
$var wire 1 ! Y $end
$var reg 1 " clk $end
$var reg 1 # enable $end
$var reg 1 $ reset $end
$scope module U1 $end
$var wire 1 " clk $end
$var wire 1 # enable $end
$var wire 1 % jumper $end
$var wire 1 $ reset $end
$var wire 1 ! Q $end
$scope module U1 $end
$var wire 1 % D $end
$var wire 1 " clk $end
$var wire 1 # enable $end
$var wire 1 $ reset $end
$var reg 1 ! Q $end
$upscope $end
$upscope $end
$upscope $end
$enddefinitions $end
#0
$dumpvars
1%
0$
x#
0"
0!
$end
#1
0%
1!
1"
1#
#2
0"
#3
1%
0!
1"
#4
0"
#5
0%
1!
1"
#6
0"
#7
1%
0!
1"
#8
0"
#9
1"
0#
#10
0"
#11
1"
#12
0"
#13
0%
1!
1"
1#
#14
0"
#15
1%
0!
1"
