Lab 03/Tabla03_POS/tabla03POS.v
module tabla03POS();

//SOP tabla03POS

  wire outAN,outBN,outCN,out01,out02,out03,out04,out05,out06,out07,out08,outres;

  reg inA,inB,inC,inD;

  not U1 (outAN, inA);
  not U2 (outBN, inB);
  not U3 (outCN, inC);
  not U3 (outDN, inD);

// Products of sum
  or U4 (out01,inA,outBN,inC,inD);
  or U5 (out02,inA,outBN,inC,outDN);
  or U6 (out03,inA,outBN,outCN,inD);
  or U7 (out04,inA,outBN,outCN,outDN);
  or U8 (out05,outAN,inB,inC,outDN);
  or U9 (out06,outAN,inB,outCN,outDN);
  or U10 (out07,outAN,outBN,inC,inD);
  or U11 (out08,outAN,outBN,inC,outDN);
  or U11 (out09,outAN,outBN,outCN,outDN);

  and UR(outres,out01,out02,out03,out04,out05,out06,out07,out08,out09);

  initial begin

    $display("A B C D| Y");
    $display("----------");
    $monitor("%b %b %b %b %b",inA,inB,inC,inD,outres);
       inA=0; inB=0; inC=0; inD=0;
    #1 inA=0; inB=0; inC=0; inD=1;
    #1 inA=0; inB=0; inC=1; inD=0;
    #1 inA=0; inB=0; inC=1; inD=1;
    #1 inA=0; inB=1; inC=0; inD=0;
    #1 inA=0; inB=1; inC=0; inD=1;
    #1 inA=0; inB=1; inC=1; inD=0;
    #1 inA=0; inB=1; inC=1; inD=1;
    #1 inA=1; inB=0; inC=0; inD=0;
    #1 inA=1; inB=0; inC=0; inD=1;
    #1 inA=1; inB=0; inC=1; inD=0;
    #1 inA=1; inB=0; inC=1; inD=1;
    #1 inA=1; inB=1; inC=0; inD=0;
    #1 inA=1; inB=1; inC=0; inD=1;
    #1 inA=1; inB=1; inC=1; inD=0;
    #1 inA=1; inB=1; inC=1; inD=1;



    $finish;
  end

//no olvidar el cambio de archivo
  initial
    begin
      $dumpfile("tabla03POS_tb.vcd");
      $dumpvars(0,tabla03POS);
  end

endmodule

Lab 03/Tabla03_POS/tabla03POS_tb.vcd
$date
	Sat Aug 01 00:25:45 2020
$end
$version
	Icarus Verilog
$end
$timescale
	1ps
$end
$scope module tabla03POS $end
$var wire 1 ! out01 $end
$var wire 1 " out02 $end
$var wire 1 # out03 $end
$var wire 1 $ out04 $end
$var wire 1 % out05 $end
$var wire 1 & out06 $end
$var wire 1 ' out07 $end
$var wire 1 ( out08 $end
$var wire 1 ) out09 $end
$var wire 1 * outAN $end
$var wire 1 + outBN $end
$var wire 1 , outCN $end
$var wire 1 - outDN $end
$var wire 1 . outres $end
$var reg 1 / inA $end
$var reg 1 0 inB $end
$var reg 1 1 inC $end
$var reg 1 2 inD $end
$upscope $end
$enddefinitions $end
#0
$dumpvars
02
01
00
0/
1.
1-
1,
1+
1*
1)
1(
1'
1&
1%
1$
1#
1"
1!
$end
#1
0-
12
#2
1-
0,
02
11
#3
0-
12
#4
0.
1-
1"
0!
1,
0+
02
01
10
#5
0"
1!
0-
12
#6
0#
1-
1"
0,
02
11
#7
0$
1#
0-
12
#8
1.
1-
1,
1&
1%
1+
1$
0*
02
01
00
1/
#9
0.
0%
0-
12
#10
1.
1-
1%
0,
02
11
#11
0.
0&
0-
12
#12
1-
1(
0'
1,
1&
0+
02
01
10
#13
0(
1'
0-
12
#14
1.
1-
1(
0,
02
11
#15
0.
0)
0-
12
