Lab 03/Tabla 02_POS/tabla02POS.v
module tabla02POS();

//SOP tabla02POS

  wire outAN,outBN,outCN,out01,out02,out03,out04,out05,outres;

  reg inA,inB,inC;

  not U1 (outAN, inA);
  not U2 (outBN, inB);
  not U3 (outCN, inC);

//Product of Sums
  or U4 (out01,inA,inB,inC);
  or U5 (out02,inA,outBN,inC);
  or U6 (out03,inA,outBN,outCN);
  or U7 (out04,outAN,inB,inC);
  or U8 (out05,outAN,inB,outCN);
  and UR(outres,out01,out02,out03,out04,out05);

  initial begin

    $display("A B C | Y");
    $display("---------");
    $monitor("%b %b %b %b",inA,inB,inC,outres);
       inA=0; inB=0; inC=0;
    #1 inA=0; inB=0; inC=1;
    #1 inA=0; inB=1; inC=0;
    #1 inA=0; inB=1; inC=1;
    #1 inA=1; inB=0; inC=0;
    #1 inA=1; inB=0; inC=1;
    #1 inA=1; inB=1; inC=0;
    #1 inA=1; inB=1; inC=1;
    $finish;
  end

//no olvidar el cambio de archivo
  initial
    begin
      $dumpfile("tabla02POS_tb.vcd");
      $dumpvars(0,tabla02POS);
  end

endmodule

Lab 03/Tabla 02_POS/tabla02POS_tb.vcd
$date
	Fri Jul 31 23:49:38 2020
$end
$version
	Icarus Verilog
$end
$timescale
	1ps
$end
$scope module tabla02POS $end
$var wire 1 ! out01 $end
$var wire 1 " out02 $end
$var wire 1 # out03 $end
$var wire 1 $ out04 $end
$var wire 1 % out05 $end
$var wire 1 & outAN $end
$var wire 1 ' outBN $end
$var wire 1 ( outCN $end
$var wire 1 ) outres $end
$var reg 1 * inA $end
$var reg 1 + inB $end
$var reg 1 , inC $end
$upscope $end
$enddefinitions $end
#0
$dumpvars
0,
0+
0*
0)
1(
1'
1&
1%
1$
1#
1"
0!
$end
#1
1)
1!
0(
1,
#2
0)
0"
1(
0'
0,
1+
#3
0#
1"
0(
1,
#4
1(
1%
0$
1'
1#
0&
0,
0+
1*
#5
0%
1$
0(
1,
#6
1)
1(
1%
0'
0,
1+
#7
0(
1,
