Lab 04/Verilog Ejercicio 5/Ejercicio.v
//Diego Alejandro Mendez
//Carnet 19673
//Ejercicio 05

module MK_GL(input wire A,B,C, output wire Y);
//Mapa Karnaugh con Gate Modeling

  wire out01, out02, out03, out04, out05, AN, BN, CN;

//Not's
  not U1(AN,A);
  not U2(BN,B);
  not U3(CN,C);

//Compuerta
  and U4(out01,A,C);
  and U5(out02,A,BN);
  or U6(Y, out01, out02);

endmodule //MK_GL

module MK_OP(input wire A,B,C, output wire Y);
//Mapa de Karnaugh con Operadores

  assign Y= (A & C) | (A & ~B);

endmodule //MK_OP

module SOP_GL(input wire A,B,C, output wire Y);
//SOP con Gate Modeling

wire out01, out02, out03, out04, out05, AN, BN, CN;

//Not's
  not U1(AN,A);
  not U2(BN,B);
  not U3(CN,C);

//Compuerta
  and U4(out01,A,BN,CN);
  and U5(out02,A,BN,C);
  and U6(out03,A,B,C);
  or U6(Y, out01, out02, out03);

endmodule // SOP_GL

module SOP_OP (input wire A,B,C, output wire Y);
//SOP  con Operadores

  assign Y = (A & ~B & ~C) | (A & ~B & C) | (A & B & C);

endmodule // SOP_OP

module POS_GL (input wire A,B,C, output wire Y);
//POS con Gate
  wire out01, out02, out03, out04, out05, AN, BN, CN;

//Not's
  not U1(AN,A);
  not U2(BN,B);
  not U3(CN,C);

//Compuerta
  or U4(out01,A,B,C);
  or U5(out02,A,B,CN);
  or U6(out03,A,BN,C);
  or U6(out04,A,BN,CN);
  or U7(out05,AN,BN,C);
  and U8(Y,out01, out02, out03, out04, out05);

endmodule //POS_GL

module POS_OP (input wire A,B,C, output wire Y);
//POS con Operadores

  assign Y = (A | B | C) & (A | B | ~C) & (A | ~B | C) & (A | ~B | ~C) & (~A | ~B | C);

endmodule //POS_OP

Lab 04/Verilog Ejercicio 5/Ejercicio_tb.v
//Diego Alejandro Mendez
//Carnet 19673
//Ejercicio 05

module testbench();
// registrar entradas
  reg inA1, inB1, inC1;
  reg inA2, inB2, inC2;
  reg inA3, inB3, inC3;
  reg inA4, inB4, inC4;
  reg inA5, inB5, inC5;
  reg inA6, inB6, inC6;

  wire Y1, Y2, Y3, Y4, Y5, Y6;

  MK_GL U1(inA1, inB1, inC1, Y1);
  MK_OP U2(inA2, inB2, inC2, Y2);
  SOP_GL U3(inA3, inB3, inC3, Y3);
  SOP_OP U4(inA4, inB4, inC4, Y4);
  POS_GL U5(inA5, inB5, inC5, Y5);
  POS_OP U6(inA6, inB6, inC6, Y6);


  initial begin //iniciamos el módulo MK_GL
    $display(" ");
    $display("Mapa Karnaugh de Gate Modeling");
    $display("A B C | Y");
    $display("----------");
    $monitor("%b %b %b  %b",inA1,inB1,inC1,Y1);
       inA1=0; inB1=0; inC1=0;
    #1 inA1=0; inB1=0; inC1=1;
    #1 inA1=0; inB1=1; inC1=0;
    #1 inA1=0; inB1=1; inC1=1;
    #1 inA1=1; inB1=0; inC1=0;
    #1 inA1=1; inB1=0; inC1=1;
    #1 inA1=1; inB1=1; inC1=0;
    #1 inA1=1; inB1=1; inC1=1;
    end

  initial begin   //iniciamos el módulo MK_OP
    #9
    $display("");
    $display("Mapa Karnaugh de Operadores");
    $display("A B C | Y");
    $display("----------");
    $monitor("%b %b %b  %b",inA2,inB2,inC2,Y2);
       inA2=0; inB2=0; inC2=0;
    #1 inA2=0; inB2=0; inC2=1;
    #1 inA2=0; inB2=1; inC2=0;
    #1 inA2=0; inB2=1; inC2=1;
    #1 inA2=1; inB2=0; inC2=0;
    #1 inA2=1; inB2=0; inC2=1;
    #1 inA2=1; inB2=1; inC2=0;
    #1 inA2=1; inB2=1; inC2=1;
    end

  initial begin
    #18
    $display(" ");         //iniciamos el módulo SOP_GL
    $display("SOP con Gate Modeling");
    $display("A B C  | Y");
    $display("----------");
    $monitor("%b %b %b  %b",inA3,inB3,inC3,Y3);
      inA3=0; inB3=0; inC3=0;
    #1 inA3=0; inB3=0; inC3=1;
    #1 inA3=0; inB3=1; inC3=0;
    #1 inA3=0; inB3=1; inC3=1;
    #1 inA3=1; inB3=0; inC3=0;
    #1 inA3=1; inB3=0; inC3=1;
    #1 inA3=1; inB3=1; inC3=0;
    #1 inA3=1; inB3=1; inC3=1;
    end

  initial begin           //iniciamos el SOP con Operadores
    #27
      $display(" ");
      $display("SOP con Operadores");
      $display("A B C | Y");
      $display("----------");
      $monitor("%b %b %b  %b",inA4,inB4,inC4,Y4);
        inA4=0; inB4=0; inC4=0;
      #1 inA4=0; inB4=0; inC4=1;
      #1 inA4=0; inB4=1; inC4=0;
      #1 inA4=0; inB4=1; inC4=1;
      #1 inA4=1; inB4=0; inC4=0;
      #1 inA4=1; inB4=0; inC4=1;
      #1 inA4=1; inB4=1; inC4=0;
      #1 inA4=1; inB4=1; inC4=1;
    end

    initial begin           //iniciamos el POS con Gate Modeling
      #36
        $display(" ");
        $display("POS con Gate Modeling");
        $display("A B C | Y");
        $display("----------");
        $monitor("%b %b %b  %b",inA5,inB5,inC5,Y5);
          inA5=0; inB5=0; inC5=0;
        #1 inA5=0; inB5=0; inC5=1;
        #1 inA5=0; inB5=1; inC5=0;
        #1 inA5=0; inB5=1; inC5=1;
        #1 inA5=1; inB5=0; inC5=0;
        #1 inA5=1; inB5=0; inC5=1;
        #1 inA5=1; inB5=1; inC5=0;
        #1 inA5=1; inB5=1; inC5=1;
      end

      initial begin
        #45
          $display(" ");         //iniciamos el módulo POS con Operadores
          $display("POS con Operadores");
          $display("A B C | Y");
          $display("----------");
          $monitor("%b %b %b   %b",inA6,inB6,inC6,Y6);
          inA6=0; inB6=0; inC6=0;
       #1 inA6=0; inB6=0; inC6=1;
       #1 inA6=0; inB6=1; inC6=0;
       #1 inA6=0; inB6=1; inC6=1;
       #1 inA6=1; inB6=0; inC6=0;
       #1 inA6=1; inB6=0; inC6=1;
       #1 inA6=1; inB6=1; inC6=0;
       #1 inA6=1; inB6=1; inC6=1;
        end

  initial
  #54 $finish;

  initial begin

      $dumpfile("Ejercicio_tb.vcd");
      $dumpvars(0,testbench);
  end

  endmodule

Lab 04/Verilog Ejercicio 5/Ejercicio_tb.vcd
$date
	Sat Aug 08 21:07:13 2020
$end
$version
	Icarus Verilog
$end
$timescale
	1ps
$end
$scope module testbench $end
$var wire 1 ! Y6 $end
$var wire 1 " Y5 $end
$var wire 1 # Y4 $end
$var wire 1 $ Y3 $end
$var wire 1 % Y2 $end
$var wire 1 & Y1 $end
$var reg 1 ' inA1 $end
$var reg 1 ( inA2 $end
$var reg 1 ) inA3 $end
$var reg 1 * inA4 $end
$var reg 1 + inA5 $end
$var reg 1 , inA6 $end
$var reg 1 - inB1 $end
$var reg 1 . inB2 $end
$var reg 1 / inB3 $end
$var reg 1 0 inB4 $end
$var reg 1 1 inB5 $end
$var reg 1 2 inB6 $end
$var reg 1 3 inC1 $end
$var reg 1 4 inC2 $end
$var reg 1 5 inC3 $end
$var reg 1 6 inC4 $end
$var reg 1 7 inC5 $end
$var reg 1 8 inC6 $end
$scope module U1 $end
$var wire 1 ' A $end
$var wire 1 9 AN $end
$var wire 1 - B $end
$var wire 1 : BN $end
$var wire 1 3 C $end
$var wire 1 ; CN $end
$var wire 1 & Y $end
$var wire 1 < out01 $end
$var wire 1 = out02 $end
$upscope $end
$scope module U2 $end
$var wire 1 ( A $end
$var wire 1 . B $end
$var wire 1 4 C $end
$var wire 1 % Y $end
$upscope $end
$scope module U3 $end
$var wire 1 ) A $end
$var wire 1 > AN $end
$var wire 1 / B $end
$var wire 1 ? BN $end
$var wire 1 5 C $end
$var wire 1 @ CN $end
$var wire 1 $ Y $end
$var wire 1 A out01 $end
$var wire 1 B out02 $end
$var wire 1 C out03 $end
$upscope $end
$scope module U4 $end
$var wire 1 * A $end
$var wire 1 0 B $end
$var wire 1 6 C $end
$var wire 1 # Y $end
$upscope $end
$scope module U5 $end
$var wire 1 + A $end
$var wire 1 D AN $end
$var wire 1 1 B $end
$var wire 1 E BN $end
$var wire 1 7 C $end
$var wire 1 F CN $end
$var wire 1 " Y $end
$var wire 1 G out01 $end
$var wire 1 H out02 $end
$var wire 1 I out03 $end
$var wire 1 J out04 $end
$var wire 1 K out05 $end
$upscope $end
$scope module U6 $end
$var wire 1 , A $end
$var wire 1 2 B $end
$var wire 1 8 C $end
$var wire 1 ! Y $end
$upscope $end
$upscope $end
$enddefinitions $end
#0
$dumpvars
xK
xJ
xI
xH
xG
xF
xE
xD
xC
xB
xA
x@
x?
x>
0=
0<
1;
1:
19
x8
x7
x6
x5
x4
03
x2
x1
x0
x/
x.
0-
x,
x+
x*
x)
x(
0'
0&
x%
x$
x#
x"
x!
$end
#1
0;
13
#2
1;
0:
03
1-
#3
0;
13
#4
1&
1=
1;
1:
09
03
0-
1'
#5
0;
1<
13
#6
0&
0=
1;
0<
0:
03
1-
#7
1&
0;
1<
13
#9
0%
04
0.
0(
#10
14
#11
04
1.
#12
14
#13
1%
04
0.
1(
#14
14
#15
0%
04
1.
#16
1%
14
#18
0$
1@
1?
1>
0A
0B
0C
05
0/
0)
#19
0@
15
#20
1@
0?
05
1/
#21
0@
15
#22
1$
1A
1@
1?
0>
05
0/
1)
#23
0A
0@
1B
15
#24
0$
1@
0B
0?
05
1/
#25
1$
0@
1C
15
#27
0#
06
00
0*
#28
16
#29
06
10
#30
16
#31
1#
06
00
1*
#32
16
#33
0#
06
10
#34
1#
16
#36
0"
1H
1I
1J
1F
1K
1E
1D
0G
07
01
0+
#37
0"
0H
0F
1G
17
#38
1F
0I
0E
1H
07
11
#39
0"
0J
0F
1I
17
#40
1"
1F
1E
0D
1J
07
01
1+
#41
0F
17
#42
0"
1F
0K
0E
07
11
#43
1"
0F
1K
17
#45
0!
08
02
0,
#46
18
#47
08
12
#48
18
#49
1!
08
02
1,
#50
18
#51
0!
08
12
#52
1!
18
