Lab 03/Tabla 04_SOP/tabla04SOP.v
module tabla04SOP();

//SOP tabla04SOP

  wire outAN,outBN,outCN,out01,out02,out03,out04,out05,out06,out07,out08,outres;

  reg inA,inB,inC,inD;

  not U1 (outAN, inA);
  not U2 (outBN, inB);
  not U3 (outCN, inC);
  not U3 (outDN, inD);

// Sum of Products
  and U4 (out01,outAN,outBN,outCN,outDN);
  and U5 (out02,outAN,outBN,inC,outDN);
  and U6 (out03,outAN,outBN,inC,inD);
  and U7 (out04,outAN,inB,inC,outDN);
  and U8 (out05,outAN,inB,inC,inD);
  and U9 (out06,inA,outBN,outCN,outDN);
  and U10 (out07,inA,outBN,outCN,inD);
  and U11 (out08,inA,outBN,inC,outDN);

  or UR(outres,out01,out02,out03,out04,out05,out06,out07,out08,out09);

  initial begin

    $display("A B C D| Y");
    $display("----------");
    $monitor("%b %b %b %b %b",inA,inB,inC,inD,outres);
       inA=0; inB=0; inC=0; inD=0;
    #1 inA=0; inB=0; inC=0; inD=1;
    #1 inA=0; inB=0; inC=1; inD=0;
    #1 inA=0; inB=0; inC=1; inD=1;
    #1 inA=0; inB=1; inC=0; inD=0;
    #1 inA=0; inB=1; inC=0; inD=1;
    #1 inA=0; inB=1; inC=1; inD=0;
    #1 inA=0; inB=1; inC=1; inD=1;
    #1 inA=1; inB=0; inC=0; inD=0;
    #1 inA=1; inB=0; inC=0; inD=1;
    #1 inA=1; inB=0; inC=1; inD=0;
    #1 inA=1; inB=0; inC=1; inD=1;
    #1 inA=1; inB=1; inC=0; inD=0;
    #1 inA=1; inB=1; inC=0; inD=1;
    #1 inA=1; inB=1; inC=1; inD=0;
    #1 inA=1; inB=1; inC=1; inD=1;



    $finish;
  end

//no olvidar el cambio de archivo
  initial
    begin
      $dumpfile("tabla04SOP_tb.vcd");
      $dumpvars(0,tabla04SOP);
  end

endmodule

Lab 03/Tabla 04_SOP/tabla04SOP_tb.vcd
$date
	Sat Aug 01 00:37:48 2020
$end
$version
	Icarus Verilog
$end
$timescale
	1ps
$end
$scope module tabla04SOP $end
$var wire 1 ! out01 $end
$var wire 1 " out02 $end
$var wire 1 # out03 $end
$var wire 1 $ out04 $end
$var wire 1 % out05 $end
$var wire 1 & out06 $end
$var wire 1 ' out07 $end
$var wire 1 ( out08 $end
$var wire 1 ) out09 $end
$var wire 1 * outAN $end
$var wire 1 + outBN $end
$var wire 1 , outCN $end
$var wire 1 - outDN $end
$var wire 1 . outres $end
$var reg 1 / inA $end
$var reg 1 0 inB $end
$var reg 1 1 inC $end
$var reg 1 2 inD $end
$upscope $end
$enddefinitions $end
#0
$dumpvars
02
01
00
0/
1.
1-
1,
1+
1*
z)
0(
0'
0&
0%
0$
0#
0"
1!
$end
#1
x.
0!
0-
12
#2
1.
1"
1-
0,
02
11
#3
0"
1#
0-
12
#4
x.
1-
0#
1,
0+
02
01
10
#5
0-
12
#6
1.
1$
1-
0,
02
11
#7
0$
1%
0-
12
#8
1&
1-
1,
0%
1+
0*
02
01
00
1/
#9
0&
1'
0-
12
#10
1(
0'
1-
0,
02
11
#11
x.
0(
0-
12
#12
1-
1,
0+
02
01
10
#13
0-
12
#14
1-
0,
02
11
#15
0-
12
