Lab 09/BufferTri4B/Buffer4B.v
//Ejercicio 4
//Diego A. Méndez

module TriBuff(input wire[3:0] A, input wire EN, output wire[3:0] Y);

 assign Y= EN ? A : 4'bz;

endmodule // TriBuff

Lab 09/BufferTri4B/Buffer4B_tb.v
//Diego A. Méndez
//Ejercicio2
//TestBench
module testbench();

  reg[3:0] A;
  reg enable;
  wire[3:0] Y;


//Llamamos al modelo FSM
      TriBuff U1(A, enable, Y);


      initial begin //iniciamos el display
      #1
            $display(" ");
            $display("  ");
            $display(" ");
            $display(" A   |  EN  |   Y");
            $display("-------------------------");
            $monitor("  %b |  %b  |  %b  ", A , enable, Y);
                A=0000; enable=1;
            #1  A=0010; enable=1;
            #1  A=0110; enable=1;
            #1  A=1100; enable=1;
            #1  A=1010; enable=0;
            #1  A=0110; enable=0;
            #1  A=0000; enable=1;
            #1  A=1111; enable=1;
            #1  A=1101; enable=1;
            //

            //  #2 reset=1;

          end

        initial
        #15 $finish;

        initial begin
          $dumpfile("Buffer4B_tb.vcd");
          $dumpvars(0, testbench);
        end

      endmodule

Lab 09/BufferTri4B/Buffer4B_tb.vcd
$date
	Sat Oct 31 09:33:13 2020
$end
$version
	Icarus Verilog
$end
$timescale
	1ps
$end
$scope module testbench $end
$var wire 4 ! Y [3:0] $end
$var reg 4 " A [3:0] $end
$var reg 1 # enable $end
$scope module U1 $end
$var wire 4 $ A [3:0] $end
$var wire 1 # EN $end
$var wire 4 % Y [3:0] $end
$upscope $end
$upscope $end
$enddefinitions $end
#0
$dumpvars
bx %
bx $
x#
bx "
bx !
$end
#1
b0 !
b0 %
1#
b0 "
b0 $
#2
b1010 !
b1010 %
b1010 "
b1010 $
#3
b1110 !
b1110 %
b1110 "
b1110 $
#4
b1100 !
b1100 %
b1100 "
b1100 $
#5
bz !
bz %
0#
b10 "
b10 $
#6
b1110 "
b1110 $
#7
b0 !
b0 %
1#
b0 "
b0 $
#8
b111 !
b111 %
b111 "
b111 $
#9
b1101 !
b1101 %
b1101 "
b1101 $
