Lab 06/Ejercicio 5/FFD.v
//Diego A. Méndez
//Ejercicio 5

//FlipFlop 4 Bits
module ffD(input clk, reset, set,
           input[3:0] D,
           output reg[3:0] Q);



    always @(posedge clk, posedge reset, posedge set) begin
      //Hacemos que el reset haga Q = 0

      //Hacemos que el set haga Q=
      if (reset) begin
        Q <= 4'b0;
        end
      else if (set) begin
        Q <= 4'b1111;
        end
      else
        Q <= D;
      end
      //Hacemos que Q se vuelva D




endmodule

Lab 06/Ejercicio 5/FFD_tb.v
//Diego A. Méndez
//TestBench Ejercicio5

module testbench();

  reg clk, reset, set;
  reg[3:0] D;
  wire[3:0] Q;

    always
      begin
      #1 clk <= 1; set<=0 ;#1 clk<=0; set<=1; #1;
      end

    ffD U1(clk, reset, set, D, Q);


     initial begin //iniciamos el mux8_1
      $display(" ");
      $display("  ");
      $display(" ");
      $display("CLK | RST | D | Q");
      $display("----------");
      $monitor("%b | %b | %b | %b",clk ,reset, D, Q);
           set=1; reset<=0;
        #1 set=0;
        #1 D<=001;
        #1 D<=010;
        #1 D<=011;
        #1 D<=100;
        #1 D<=101;
        #1 D<=110;
        #1 D<=111;
        #1 reset<=1;
        #1 reset<=0;

        end

  initial
  #10 $finish;

  initial begin
    $dumpfile("FFD_tb.vcd");
    $dumpvars(0, testbench);
  end

endmodule

Lab 06/Ejercicio 5/FFD_tb.vcd
$date
	Sat Sep 05 00:24:16 2020
$end
$version
	Icarus Verilog
$end
$timescale
	1ps
$end
$scope module testbench $end
$var wire 4 ! Q [3:0] $end
$var reg 4 " D [3:0] $end
$var reg 1 # clk $end
$var reg 1 $ reset $end
$var reg 1 % set $end
$scope module U1 $end
$var wire 4 & D [3:0] $end
$var wire 1 # clk $end
$var wire 1 $ reset $end
$var wire 1 % set $end
$var reg 4 ' Q [3:0] $end
$upscope $end
$upscope $end
$enddefinitions $end
#0
$dumpvars
b1111 '
bx &
1%
0$
x#
bx "
b1111 !
$end
#1
bx !
bx '
1#
0%
#2
b1111 !
b1111 '
b1 "
b1 &
1%
0#
#3
b1010 "
b1010 &
#4
b1011 !
b1011 '
b1011 "
b1011 &
0%
1#
#5
b1111 !
b1111 '
b100 "
b100 &
1%
0#
#6
b101 "
b101 &
#7
b1110 !
b1110 '
b1110 "
b1110 &
0%
1#
#8
b1111 !
b1111 '
b1111 "
b1111 &
1%
0#
#9
b0 !
b0 '
1$
#10
b1111 !
b1111 '
0$
0%
1#
