Lab 08/Ejercicio 2 Memoria ROM/Memoria.v
//Diego A. Méndez
//Ejercicio 2
//Memoria ROM


module memoria(input wire[11:0] address, output wire [7:0] data);

reg[7:0] memory[0:4095];

  initial begin
//recordar hacer la lista con .list
 $readmemb("EPROM.list", memory);
  end

 assign data = memory[address];

endmodule

Lab 08/Ejercicio 2 Memoria ROM/Memoria_tb.v
module testbench();

  reg[11:0] address;
  wire[7:0] data;

//No necesita de un clock
//Llamamos al modulo de memoria
      memoria U1(address, data);


      initial begin //iniciamos el display
            #1
            $display(" ");
            $display("  ");
            $display(" ");
            $display("|  ADDRESS  |   DATA    | ");
            $display("----------------------------");
            $monitor("| %b | %b | ", address, data);
              address=12'b000000000000;
           #1 address=12'b000000000001;
           #1 address=12'b000000000010;
           #1 address=12'b000000000011;
           #1 address=12'b000000000100;
           #1 address=12'b000000000101;
           #1 address=12'b000000000110;
           #1 address=12'b000000000111;
           #1 address=12'b000000001000;
           #1 address=12'b000000001001;
           #1 address=12'b000000001010;

          end

        initial
        #50 $finish;

        initial begin
          $dumpfile("Memoria_tb.vcd");
          $dumpvars(0, testbench);
        end

      endmodule

Lab 08/Ejercicio 2 Memoria ROM/Memoria_tb.vcd
$date
	Sat Oct 24 02:49:58 2020
$end
$version
	Icarus Verilog
$end
$timescale
	1ps
$end
$scope module testbench $end
$var wire 8 ! data [7:0] $end
$var reg 12 " address [11:0] $end
$scope module U1 $end
$var wire 12 # address [11:0] $end
$var wire 8 $ data [7:0] $end
$upscope $end
$upscope $end
$enddefinitions $end
#0
$dumpvars
bx $
bx #
bx "
bx !
$end
#1
b10101010 !
b10101010 $
b0 "
b0 #
#2
b10011001 !
b10011001 $
b1 "
b1 #
#3
b11010011 !
b11010011 $
b10 "
b10 #
#4
b11110000 !
b11110000 $
b11 "
b11 #
#5
b10011110 !
b10011110 $
b100 "
b100 #
#6
b11111111 !
b11111111 $
b101 "
b101 #
#7
b11100110 !
b11100110 $
b110 "
b110 #
#8
b111100 !
b111100 $
b111 "
b111 #
#9
b10000000 !
b10000000 $
b1000 "
b1000 #
#10
b101001 !
b101001 $
b1001 "
b1001 #
#11
b101010 !
b101010 $
b1010 "
b1010 #
