Lab 09/FlipflopD 2bit/FFD2B.v
//Diego A. Méndez
//Ejercicio 1

//FlipFlop de 2bit
module ffD(input clk, reset, enable, input D, output reg Q);

    always @(posedge clk, posedge reset) begin
      //Hacemos que el reset haga Q = 0
      if (reset) begin
        Q <= 0;
        end
      //Hacemos que el Enable funcione
      else if (enable) begin
        Q <= D;
        end
      end //Always

endmodule

module ffD2B (input clk, reset, enable, input[1:0] D, output wire[1:0] Q);

    ffD U2(clk, reset, enable, D[1], Q[1]);
    ffD U1(clk, reset, enable, D[0], Q[0]);

endmodule // ffD2B

Lab 09/FlipflopD 2bit/FFD2B_tb.v
//Diego A. Méndez
//Testbench FFD 2 bits

module testbench();

  reg clk, reset, enable;
  reg[1:0] A;
  wire[1:0] Y;

//Iniciamos el clock
    always
      begin
      clk <= 0; reset<=0; #1 clk<=1; #1;

      end
//Llamamos al modelo FSM
      ffD2B U1(clk, reset, enable, A, Y);


      initial begin //iniciamos el display
            $display(" ");
            $display("  ");
            $display(" ");
            $display(" CLK | RST | EN | A | Y");
            $display("-------------------------");
            $monitor("  %b |  %b  |  %b  |  %b  | %b",clk ,reset, enable, A, Y);
               A=00; enable=1;
            #2 A=00; enable=1;
            #2 A=10; enable=1;
            #2 A=00; enable=0;
            #2 A=00; enable=1;
            #2 A=00; enable=1;
            #2 A=10; enable=1;
            #2 A=11; enable=1;
            #2 A=10; enable=1;
            //

            //  #2 reset=1;

          end

        initial
        #18 $finish;

        initial begin
          $dumpfile("FFD2B_tb.vcd");
          $dumpvars(0, testbench);
        end

      endmodule

Lab 09/FlipflopD 2bit/FFD2B_tb.vcd
$date
	Sat Oct 31 10:33:58 2020
$end
$version
	Icarus Verilog
$end
$timescale
	1ps
$end
$scope module testbench $end
$var wire 2 ! Y [1:0] $end
$var reg 2 " A [1:0] $end
$var reg 1 # clk $end
$var reg 1 $ enable $end
$var reg 1 % reset $end
$scope module U1 $end
$var wire 2 & D [1:0] $end
$var wire 1 # clk $end
$var wire 1 $ enable $end
$var wire 1 % reset $end
$var wire 2 ' Q [1:0] $end
$scope module U1 $end
$var wire 1 ( D $end
$var wire 1 # clk $end
$var wire 1 $ enable $end
$var wire 1 % reset $end
$var reg 1 ) Q $end
$upscope $end
$scope module U2 $end
$var wire 1 * D $end
$var wire 1 # clk $end
$var wire 1 $ enable $end
$var wire 1 % reset $end
$var reg 1 + Q $end
$upscope $end
$upscope $end
$upscope $end
$enddefinitions $end
#0
$dumpvars
x+
0*
x)
0(
bx '
b0 &
0%
1$
0#
b0 "
bx !
$end
#1
0+
b0 !
b0 '
0)
1#
#2
0#
#3
1#
#4
0#
1*
b10 "
b10 &
#5
b10 !
b10 '
1+
1#
#6
0#
0*
0$
b0 "
b0 &
#7
1#
#8
0#
1$
#9
b0 !
b0 '
0+
1#
#10
0#
#11
1#
#12
0#
1*
b10 "
b10 &
#13
b10 !
b10 '
1+
1#
#14
0#
1(
b11 "
b11 &
#15
b11 !
b11 '
1)
1#
#16
0#
0(
b10 "
b10 &
#17
b10 !
b10 '
0)
1#
