Lab 03/Tabla 03_SOP/tabla03SOP.v
module tabla03SOP();

//SOP tabla03SOP

  wire outAN,outBN,outCN,out01,out02,out03,out04,out05,out06,out07,out08,outres;

  reg inA,inB,inC,inD;

  not U1 (outAN, inA);
  not U2 (outBN, inB);
  not U3 (outCN, inC);
  not U3 (outDN, inD);

//Sum of Products
  and U4 (out01,outAN,outBN,outCN,outDN);
  and U5 (out02,outAN,outBN,outCN,inD);
  and U6 (out03,outAN,outBN,inC,outDN);
  and U7 (out04,outAN,outBN,inC,inD);
  and U8 (out05,inA,outBN,outCN,outDN);
  and U9 (out06,inA,outBN,inC,outDN);
  and U10 (out07,inA,inB,inC,outDN);

  or UR(outres,out01,out02,out03,out04,out05,out06,out07);

  initial begin

    $display("A B C D| Y");
    $display("----------");
    $monitor("%b %b %b %b %b",inA,inB,inC,inD,outres);
       inA=0; inB=0; inC=0; inD=0;
    #1 inA=0; inB=0; inC=0; inD=1;
    #1 inA=0; inB=0; inC=1; inD=0;
    #1 inA=0; inB=0; inC=1; inD=1;
    #1 inA=0; inB=1; inC=0; inD=0;
    #1 inA=0; inB=1; inC=0; inD=1;
    #1 inA=0; inB=1; inC=1; inD=0;
    #1 inA=0; inB=1; inC=1; inD=1;
    #1 inA=1; inB=0; inC=0; inD=0;
    #1 inA=1; inB=0; inC=0; inD=1;
    #1 inA=1; inB=0; inC=1; inD=0;
    #1 inA=1; inB=0; inC=1; inD=1;
    #1 inA=1; inB=1; inC=0; inD=0;
    #1 inA=1; inB=1; inC=0; inD=1;
    #1 inA=1; inB=1; inC=1; inD=0;
    #1 inA=1; inB=1; inC=1; inD=1;



    $finish;
  end

//no olvidar el cambio de archivo
  initial
    begin
      $dumpfile("tabla03SOP_tb.vcd");
      $dumpvars(0,tabla03SOP);
  end

endmodule

Lab 03/Tabla 03_SOP/tabla03SOP_tb.vcd
$date
	Sat Aug 01 00:11:38 2020
$end
$version
	Icarus Verilog
$end
$timescale
	1ps
$end
$scope module tabla03SOP $end
$var wire 1 ! out01 $end
$var wire 1 " out02 $end
$var wire 1 # out03 $end
$var wire 1 $ out04 $end
$var wire 1 % out05 $end
$var wire 1 & out06 $end
$var wire 1 ' out07 $end
$var wire 1 ( outAN $end
$var wire 1 ) outBN $end
$var wire 1 * outCN $end
$var wire 1 + outDN $end
$var wire 1 , outres $end
$var reg 1 - inA $end
$var reg 1 . inB $end
$var reg 1 / inC $end
$var reg 1 0 inD $end
$upscope $end
$enddefinitions $end
#0
$dumpvars
00
0/
0.
0-
1,
1+
1*
1)
1(
0'
0&
0%
0$
0#
0"
1!
$end
#1
0!
1"
0+
10
#2
1#
0"
1+
0*
00
1/
#3
0#
1$
0+
10
#4
0,
1+
0$
1*
0)
00
0/
1.
#5
0+
10
#6
1+
0*
00
1/
#7
0+
10
#8
1,
1%
1+
1*
1)
0(
00
0/
0.
1-
#9
0,
0%
0+
10
#10
1,
1&
1+
0*
00
1/
#11
0,
0&
0+
10
#12
1+
1*
0)
00
0/
1.
#13
0+
10
#14
1,
1'
1+
0*
00
1/
#15
0,
0'
0+
10
